nexxT/Qt.py
nexxT/QtMetaPackage.py
nexxT/__init__.py
nexxT/shiboken.py
nexxT/binary/msvc_x86_64/nonopt/cnexxT.pyd
nexxT/binary/msvc_x86_64/nonopt/nexxT.dll
nexxT/binary/msvc_x86_64/nonopt/nexxT.exp
nexxT/binary/msvc_x86_64/nonopt/nexxT.lib
nexxT/binary/msvc_x86_64/release/cnexxT.pyd
nexxT/binary/msvc_x86_64/release/nexxT.dll
nexxT/binary/msvc_x86_64/release/nexxT.exp
nexxT/binary/msvc_x86_64/release/nexxT.lib
nexxT/core/ActiveApplication.py
nexxT/core/AppConsole.py
nexxT/core/Application.py
nexxT/core/BaseFilterEnvironment.py
nexxT/core/BaseGraph.py
nexxT/core/CompositeFilter.py
nexxT/core/ConfigFileSchema.json
nexxT/core/ConfigFiles.py
nexxT/core/Configuration.py
nexxT/core/Exceptions.py
nexxT/core/FilterEnvironment.py
nexxT/core/FilterMockup.py
nexxT/core/Graph.py
nexxT/core/GuiStateSchema.json
nexxT/core/PluginManager.py
nexxT/core/PortImpl.py
nexxT/core/PropertyCollectionImpl.py
nexxT/core/PropertyHandlers.py
nexxT/core/SubConfiguration.py
nexxT/core/Thread.py
nexxT/core/Utils.py
nexxT/core/Variables.py
nexxT/core/__init__.py
nexxT/core/qrc_resources.py
nexxT/examples/__init__.py
nexxT/examples/framework/ImageBlur.py
nexxT/examples/framework/ImageData.py
nexxT/examples/framework/ImageView.py
nexxT/examples/framework/__init__.py
nexxT/examples/framework/example.json
nexxT/examples/videoplayback/config.json
nexxT/filters/GenericReader.py
nexxT/filters/__init__.py
nexxT/filters/hdf5.py
nexxT/include/nexxT/Compatibility.hpp
nexxT/include/nexxT/DataSamples.hpp
nexxT/include/nexxT/FilterEnvironment.hpp
nexxT/include/nexxT/Filters.hpp
nexxT/include/nexxT/InputPortInterface.hpp
nexxT/include/nexxT/Logger.hpp
nexxT/include/nexxT/NexxTLinkage.hpp
nexxT/include/nexxT/NexxTPlugins.hpp
nexxT/include/nexxT/OutputPortInterface.hpp
nexxT/include/nexxT/Ports.hpp
nexxT/include/nexxT/PropertyCollection.hpp
nexxT/include/nexxT/Services.hpp
nexxT/include/nexxT/SharedPointerTypes.hpp
nexxT/interface/DataSamples.py
nexxT/interface/Filters.py
nexxT/interface/Ports.py
nexxt-1.3.1.dist-info/licenses/LICENSE
nexxt-1.3.1.dist-info/licenses/NOTICE
nexxt-1.3.1.dist-info/METADATA
nexxt-1.3.1.dist-info/WHEEL
nexxt-1.3.1.dist-info/entry_points.txt
nexxt-1.3.1.dist-info/top_level.txt
nexxt-1.3.1.dist-info/RECORD
