Metadata-Version: 2.4
Name: nexxT
Version: 1.3.1
Summary: An extensible framework.
Home-page: https://github.com/ifm/nexxT
Author: Christoph Wiedemann
Author-email: 62332054+cwiede@users.noreply.github.com
License: Apache-2
License-File: LICENSE
License-File: NOTICE
Requires-Dist: PySide6==6.8.3
Requires-Dist: shiboken6==6.8.3
Requires-Dist: jsonschema>=3.2.0
Requires-Dist: h5py>=2.10.0
Requires-Dist: importlib-metadata>=3.6; python_version < "3.10"
Requires-Dist: pip-licenses
Dynamic: author
Dynamic: author-email
Dynamic: home-page
Dynamic: license
Dynamic: license-file
Dynamic: requires-dist
Dynamic: summary
